{
  "openapi": "3.0.4",
  "info": {
    "title": "APICatalogo",
    "description": "Catálogo de produtos e categorias",
    "contact": {
      "name": "Luciano Filho",
      "email": "luciano.lvbf27@hotmail.com"
    },
    "version": "v1"
  },
  "paths": {
    "/Auth/CreateRole": {
      "post": {
        "tags": [
          "Auth"
        ],
        "parameters": [
          {
            "name": "roleName",
            "in": "query",
            "schema": {
              "type": "string"
            }
          }
        ],
        "responses": {
          "200": {
            "description": "OK"
          }
        }
      }
    },
    "/Auth/AdicionaUserARole": {
      "post": {
        "tags": [
          "Auth"
        ],
        "parameters": [
          {
            "name": "email",
            "in": "query",
            "schema": {
              "type": "string"
            }
          },
          {
            "name": "role",
            "in": "query",
            "schema": {
              "type": "string"
            }
          }
        ],
        "responses": {
          "200": {
            "description": "OK"
          }
        }
      }
    },
    "/Auth/login": {
      "post": {
        "tags": [
          "Auth"
        ],
        "requestBody": {
          "content": {
            "application/json-patch+json": {
              "schema": {
                "$ref": "#/components/schemas/LoginModel"
              }
            },
            "application/json": {
              "schema": {
                "$ref": "#/components/schemas/LoginModel"
              }
            },
            "text/json": {
              "schema": {
                "$ref": "#/components/schemas/LoginModel"
              }
            },
            "application/*+json": {
              "schema": {
                "$ref": "#/components/schemas/LoginModel"
              }
            }
          }
        },
        "responses": {
          "200": {
            "description": "OK"
          }
        }
      }
    },
    "/Auth/Registro": {
      "post": {
        "tags": [
          "Auth"
        ],
        "requestBody": {
          "content": {
            "application/json-patch+json": {
              "schema": {
                "$ref": "#/components/schemas/RegisterModel"
              }
            },
            "application/json": {
              "schema": {
                "$ref": "#/components/schemas/RegisterModel"
              }
            },
            "text/json": {
              "schema": {
                "$ref": "#/components/schemas/RegisterModel"
              }
            },
            "application/*+json": {
              "schema": {
                "$ref": "#/components/schemas/RegisterModel"
              }
            }
          }
        },
        "responses": {
          "200": {
            "description": "OK"
          }
        }
      }
    },
    "/Auth/refresh-token": {
      "post": {
        "tags": [
          "Auth"
        ],
        "requestBody": {
          "content": {
            "application/json-patch+json": {
              "schema": {
                "$ref": "#/components/schemas/TokenModel"
              }
            },
            "application/json": {
              "schema": {
                "$ref": "#/components/schemas/TokenModel"
              }
            },
            "text/json": {
              "schema": {
                "$ref": "#/components/schemas/TokenModel"
              }
            },
            "application/*+json": {
              "schema": {
                "$ref": "#/components/schemas/TokenModel"
              }
            }
          }
        },
        "responses": {
          "200": {
            "description": "OK"
          }
        }
      }
    },
    "/Auth/revoke/{username}": {
      "post": {
        "tags": [
          "Auth"
        ],
        "parameters": [
          {
            "name": "username",
            "in": "path",
            "required": true,
            "schema": {
              "type": "string"
            }
          }
        ],
        "responses": {
          "200": {
            "description": "OK"
          }
        }
      }
    },
    "/Categorias": {
      "get": {
        "tags": [
          "Categorias"
        ],
        "summary": "Obtém uma lista paginada de categorias.",
        "parameters": [
          {
            "name": "skip",
            "in": "query",
            "description": "Número de itens a ignorar (paginação).",
            "schema": {
              "type": "integer",
              "format": "int32",
              "default": 0
            }
          },
          {
            "name": "take",
            "in": "query",
            "description": "Número de itens a retornar (paginação).",
            "schema": {
              "type": "integer",
              "format": "int32",
              "default": 10
            }
          }
        ],
        "responses": {
          "200": {
            "description": "OK",
            "content": {
              "text/plain": {
                "schema": {
                  "type": "array",
                  "items": {
                    "$ref": "#/components/schemas/CategoriaDTO"
                  }
                }
              },
              "application/json": {
                "schema": {
                  "type": "array",
                  "items": {
                    "$ref": "#/components/schemas/CategoriaDTO"
                  }
                }
              },
              "text/json": {
                "schema": {
                  "type": "array",
                  "items": {
                    "$ref": "#/components/schemas/CategoriaDTO"
                  }
                }
              }
            }
          }
        }
      },
      "post": {
        "tags": [
          "Categorias"
        ],
        "summary": "Cria uma nova categoria.",
        "requestBody": {
          "description": "Objeto CategoriaDTO com os dados da nova categoria.",
          "content": {
            "application/json-patch+json": {
              "schema": {
                "$ref": "#/components/schemas/CategoriaDTO"
              }
            },
            "application/json": {
              "schema": {
                "$ref": "#/components/schemas/CategoriaDTO"
              }
            },
            "text/json": {
              "schema": {
                "$ref": "#/components/schemas/CategoriaDTO"
              }
            },
            "application/*+json": {
              "schema": {
                "$ref": "#/components/schemas/CategoriaDTO"
              }
            }
          }
        },
        "responses": {
          "200": {
            "description": "OK",
            "content": {
              "text/plain": {
                "schema": {
                  "$ref": "#/components/schemas/CategoriaDTO"
                }
              },
              "application/json": {
                "schema": {
                  "$ref": "#/components/schemas/CategoriaDTO"
                }
              },
              "text/json": {
                "schema": {
                  "$ref": "#/components/schemas/CategoriaDTO"
                }
              }
            }
          }
        }
      }
    },
    "/Categorias/{id}": {
      "get": {
        "tags": [
          "Categorias"
        ],
        "summary": "Obtém uma categoria específica pelo ID.",
        "operationId": "CategoriaPorId",
        "parameters": [
          {
            "name": "id",
            "in": "path",
            "description": "ID da categoria.",
            "required": true,
            "schema": {
              "type": "integer",
              "format": "int32"
            }
          }
        ],
        "responses": {
          "200": {
            "description": "OK",
            "content": {
              "text/plain": {
                "schema": {
                  "$ref": "#/components/schemas/CategoriaDTO"
                }
              },
              "application/json": {
                "schema": {
                  "$ref": "#/components/schemas/CategoriaDTO"
                }
              },
              "text/json": {
                "schema": {
                  "$ref": "#/components/schemas/CategoriaDTO"
                }
              }
            }
          }
        }
      },
      "put": {
        "tags": [
          "Categorias"
        ],
        "summary": "Atualiza uma categoria existente.",
        "parameters": [
          {
            "name": "id",
            "in": "path",
            "description": "ID da categoria a ser atualizada.",
            "required": true,
            "schema": {
              "type": "integer",
              "format": "int32"
            }
          }
        ],
        "requestBody": {
          "description": "Objeto CategoriaDTO com os dados atualizados.",
          "content": {
            "application/json-patch+json": {
              "schema": {
                "$ref": "#/components/schemas/CategoriaDTO"
              }
            },
            "application/json": {
              "schema": {
                "$ref": "#/components/schemas/CategoriaDTO"
              }
            },
            "text/json": {
              "schema": {
                "$ref": "#/components/schemas/CategoriaDTO"
              }
            },
            "application/*+json": {
              "schema": {
                "$ref": "#/components/schemas/CategoriaDTO"
              }
            }
          }
        },
        "responses": {
          "200": {
            "description": "OK",
            "content": {
              "text/plain": {
                "schema": {
                  "$ref": "#/components/schemas/CategoriaDTO"
                }
              },
              "application/json": {
                "schema": {
                  "$ref": "#/components/schemas/CategoriaDTO"
                }
              },
              "text/json": {
                "schema": {
                  "$ref": "#/components/schemas/CategoriaDTO"
                }
              }
            }
          }
        }
      },
      "delete": {
        "tags": [
          "Categorias"
        ],
        "summary": "Remove uma categoria pelo ID.",
        "parameters": [
          {
            "name": "id",
            "in": "path",
            "description": "ID da categoria a ser removida.",
            "required": true,
            "schema": {
              "type": "integer",
              "format": "int32"
            }
          }
        ],
        "responses": {
          "200": {
            "description": "OK"
          }
        }
      }
    },
    "/Produtos": {
      "get": {
        "tags": [
          "Produtos"
        ],
        "parameters": [
          {
            "name": "skip",
            "in": "query",
            "schema": {
              "type": "integer",
              "format": "int32",
              "default": 0
            }
          },
          {
            "name": "take",
            "in": "query",
            "schema": {
              "type": "integer",
              "format": "int32",
              "default": 10
            }
          }
        ],
        "responses": {
          "200": {
            "description": "OK",
            "content": {
              "text/plain": {
                "schema": {
                  "type": "array",
                  "items": {
                    "$ref": "#/components/schemas/ProdutoDTO"
                  }
                }
              },
              "application/json": {
                "schema": {
                  "type": "array",
                  "items": {
                    "$ref": "#/components/schemas/ProdutoDTO"
                  }
                }
              },
              "text/json": {
                "schema": {
                  "type": "array",
                  "items": {
                    "$ref": "#/components/schemas/ProdutoDTO"
                  }
                }
              }
            }
          }
        }
      },
      "post": {
        "tags": [
          "Produtos"
        ],
        "requestBody": {
          "content": {
            "application/json-patch+json": {
              "schema": {
                "$ref": "#/components/schemas/ProdutoDTO"
              }
            },
            "application/json": {
              "schema": {
                "$ref": "#/components/schemas/ProdutoDTO"
              }
            },
            "text/json": {
              "schema": {
                "$ref": "#/components/schemas/ProdutoDTO"
              }
            },
            "application/*+json": {
              "schema": {
                "$ref": "#/components/schemas/ProdutoDTO"
              }
            }
          }
        },
        "responses": {
          "200": {
            "description": "OK",
            "content": {
              "text/plain": {
                "schema": {
                  "$ref": "#/components/schemas/ProdutoDTO"
                }
              },
              "application/json": {
                "schema": {
                  "$ref": "#/components/schemas/ProdutoDTO"
                }
              },
              "text/json": {
                "schema": {
                  "$ref": "#/components/schemas/ProdutoDTO"
                }
              }
            }
          }
        }
      }
    },
    "/Produtos/{id}": {
      "get": {
        "tags": [
          "Produtos"
        ],
        "operationId": "ObterProdutoPorId",
        "parameters": [
          {
            "name": "id",
            "in": "path",
            "required": true,
            "schema": {
              "type": "integer",
              "format": "int32"
            }
          }
        ],
        "responses": {
          "200": {
            "description": "OK",
            "content": {
              "text/plain": {
                "schema": {
                  "$ref": "#/components/schemas/ProdutoDTO"
                }
              },
              "application/json": {
                "schema": {
                  "$ref": "#/components/schemas/ProdutoDTO"
                }
              },
              "text/json": {
                "schema": {
                  "$ref": "#/components/schemas/ProdutoDTO"
                }
              }
            }
          }
        }
      },
      "put": {
        "tags": [
          "Produtos"
        ],
        "parameters": [
          {
            "name": "id",
            "in": "path",
            "required": true,
            "schema": {
              "type": "integer",
              "format": "int32"
            }
          }
        ],
        "requestBody": {
          "content": {
            "application/json-patch+json": {
              "schema": {
                "$ref": "#/components/schemas/ProdutoDTO"
              }
            },
            "application/json": {
              "schema": {
                "$ref": "#/components/schemas/ProdutoDTO"
              }
            },
            "text/json": {
              "schema": {
                "$ref": "#/components/schemas/ProdutoDTO"
              }
            },
            "application/*+json": {
              "schema": {
                "$ref": "#/components/schemas/ProdutoDTO"
              }
            }
          }
        },
        "responses": {
          "200": {
            "description": "OK",
            "content": {
              "text/plain": {
                "schema": {
                  "$ref": "#/components/schemas/ProdutoDTO"
                }
              },
              "application/json": {
                "schema": {
                  "$ref": "#/components/schemas/ProdutoDTO"
                }
              },
              "text/json": {
                "schema": {
                  "$ref": "#/components/schemas/ProdutoDTO"
                }
              }
            }
          }
        }
      },
      "delete": {
        "tags": [
          "Produtos"
        ],
        "parameters": [
          {
            "name": "id",
            "in": "path",
            "required": true,
            "schema": {
              "type": "integer",
              "format": "int32"
            }
          }
        ],
        "responses": {
          "200": {
            "description": "OK",
            "content": {
              "text/plain": {
                "schema": {
                  "$ref": "#/components/schemas/ProdutoDTO"
                }
              },
              "application/json": {
                "schema": {
                  "$ref": "#/components/schemas/ProdutoDTO"
                }
              },
              "text/json": {
                "schema": {
                  "$ref": "#/components/schemas/ProdutoDTO"
                }
              }
            }
          }
        }
      }
    },
    "/Produtos/{id}/updatePartial": {
      "patch": {
        "tags": [
          "Produtos"
        ],
        "parameters": [
          {
            "name": "id",
            "in": "path",
            "required": true,
            "schema": {
              "type": "integer",
              "format": "int32"
            }
          }
        ],
        "requestBody": {
          "content": {
            "application/json-patch+json": {
              "schema": {
                "type": "array",
                "items": {
                  "$ref": "#/components/schemas/Operation"
                }
              }
            },
            "application/json": {
              "schema": {
                "type": "array",
                "items": {
                  "$ref": "#/components/schemas/Operation"
                }
              }
            },
            "text/json": {
              "schema": {
                "type": "array",
                "items": {
                  "$ref": "#/components/schemas/Operation"
                }
              }
            },
            "application/*+json": {
              "schema": {
                "type": "array",
                "items": {
                  "$ref": "#/components/schemas/Operation"
                }
              }
            }
          }
        },
        "responses": {
          "200": {
            "description": "OK",
            "content": {
              "text/plain": {
                "schema": {
                  "$ref": "#/components/schemas/ProdutoDtoUpdateRequest"
                }
              },
              "application/json": {
                "schema": {
                  "$ref": "#/components/schemas/ProdutoDtoUpdateRequest"
                }
              },
              "text/json": {
                "schema": {
                  "$ref": "#/components/schemas/ProdutoDtoUpdateRequest"
                }
              }
            }
          }
        }
      }
    }
  },
  "components": {
    "schemas": {
      "CategoriaDTO": {
        "required": [
          "imagemUrl",
          "nome"
        ],
        "type": "object",
        "properties": {
          "id": {
            "type": "integer",
            "format": "int32"
          },
          "nome": {
            "maxLength": 80,
            "minLength": 0,
            "type": "string"
          },
          "imagemUrl": {
            "maxLength": 300,
            "minLength": 0,
            "type": "string"
          }
        },
        "additionalProperties": false
      },
      "LoginModel": {
        "required": [
          "password",
          "userName"
        ],
        "type": "object",
        "properties": {
          "userName": {
            "minLength": 1,
            "type": "string"
          },
          "password": {
            "minLength": 1,
            "type": "string"
          }
        },
        "additionalProperties": false
      },
      "Operation": {
        "type": "object",
        "properties": {
          "operationType": {
            "$ref": "#/components/schemas/OperationType"
          },
          "path": {
            "type": "string",
            "nullable": true
          },
          "op": {
            "type": "string",
            "nullable": true
          },
          "from": {
            "type": "string",
            "nullable": true
          },
          "value": {
            "nullable": true
          }
        },
        "additionalProperties": false
      },
      "OperationType": {
        "enum": [
          0,
          1,
          2,
          3,
          4,
          5,
          6
        ],
        "type": "integer",
        "format": "int32"
      },
      "ProdutoDTO": {
        "required": [
          "descricao",
          "imagemUrl",
          "nome",
          "preco"
        ],
        "type": "object",
        "properties": {
          "id": {
            "type": "integer",
            "format": "int32"
          },
          "nome": {
            "maxLength": 80,
            "minLength": 0,
            "type": "string"
          },
          "descricao": {
            "maxLength": 300,
            "minLength": 0,
            "type": "string"
          },
          "preco": {
            "type": "number",
            "format": "double"
          },
          "imagemUrl": {
            "maxLength": 300,
            "minLength": 0,
            "type": "string"
          },
          "categoriaId": {
            "type": "integer",
            "format": "int32"
          }
        },
        "additionalProperties": false
      },
      "ProdutoDtoUpdateRequest": {
        "type": "object",
        "properties": {
          "estoque": {
            "maximum": 9999,
            "minimum": 1,
            "type": "number",
            "format": "float"
          },
          "dataCadastro": {
            "type": "string",
            "format": "date-time"
          }
        },
        "additionalProperties": false
      },
      "RegisterModel": {
        "required": [
          "emailAddress",
          "password",
          "userName"
        ],
        "type": "object",
        "properties": {
          "userName": {
            "minLength": 1,
            "type": "string"
          },
          "emailAddress": {
            "minLength": 1,
            "type": "string",
            "format": "email"
          },
          "password": {
            "minLength": 1,
            "type": "string"
          }
        },
        "additionalProperties": false
      },
      "TokenModel": {
        "type": "object",
        "properties": {
          "tokenAcesso": {
            "type": "string",
            "nullable": true
          },
          "tokenAtualizado": {
            "type": "string",
            "nullable": true
          }
        },
        "additionalProperties": false
      }
    }
  }
}